{
	"list":[
		{
			"id":"1",
			"title":"高品质小猴图案空调被抱被 + 长颈鹿毛绒公仔玩具动物镜",
			"intro":"img/1.1intro.jpg|img/1.2intro.jpg|img/1.3intro.jpg",
			"price":"￥ 158.00",
			"num":1,
			"pic":"img/1.jpg",
			"origin":"img/cn.jpg|中国",
			"parents":"g-jr-sh-xw",
			"kind":"new",
			"code":"93649110-1",
			"bigpic":"img/1.1big.jpg|img/1.2big.jpg|img/1.3big.jpg",
			"smallpic":"img/1.1small.jpg|img/1.2small.jpg|img/1.3small.jpg",
			"colorpic":"",
			"color":""
		},
		{
			"id":"2",
			"title":"Relax 泰国进口天然乳胶 婴儿枕 1个",
			"intro":"img/1.1intro.jpg|img/1.2intro.jpg|img/1.3intro.jpg",
			"price":"￥ 141.00",
			"num":1,
			"pic":"img/2.jpg",
			"origin":"img/cn.jpg|中国",
			"parents":"g-jr-sh-xw",
			"kind":"new",
			"code":"93427783-1",
			"bigpic":"img/2.1big.jpg|img/2.2big.jpg",
			"smallpic":"img/2.1small.jpg|img/2.2small.jpg",
			"colorpic":"img/2.1color.jpg|img/2.2color.jpg",
			"color":"裸粉|淡蓝"
		},
		{
			"id":"3",
			"title":"荷兰直邮 Aptamil 德爱他美奶粉 1段 800克*2盒 全国包邮",
			"intro":"雪域牛乳芝士蛋糕雪域牛乳芝士蛋糕雪牛乳芝士蛋糕雪域牛乳芝士蛋糕",
			"price":"￥ 258.00",
			"num":1,
			"pic":"img/3.jpg",
			"origin":"img/cn.jpg|中国",
			"parents":"g-my-yn",
			"kind":"new",
			"code":"93649110-1",
			"bigpic":"img/3.1big.jpg|img/3.2big.jpg",
			"smallpic":"img/3.1small.jpg|img/3.2small.jpg",
			"colorpic":"",
			"color":""
		},
		{
			"id":"4",
			"title":"启赋奶粉",
			"intro":"img/1.1intro.jpg|img/1.2intro.jpg|img/1.3intro.jpg",
			"price":"￥ 158.00",
			"num":1,
			"pic":"img/4.jpg",
			"origin":"img/us.jpg|美国",
			"parents":"g-my-yn",
			"kind":"new",
			"code":"93649110-1",
			"bigpic":"img/4.1big.jpg",
			"smallpic":"img/4.1small.jpg",
			"colorpic":"",
			"color":""
		},
		{
			"id":"5",
			"title":"VINCI智能头机 大存储音乐播放器+Hi-Fi耳机+高精传感器",
			"intro":"img/1.1intro.jpg|img/1.2intro.jpg|img/1.3intro.jpg",
			"price":"￥ 158.00",
			"num":1,
			"pic":"img/5.jpg",
			"origin":"img/cn.jpg|中国",
			"parents":"g-jr-sh-xw",
			"kind":"new",
			"code":"93649110-1",
			"bigpic":"img/5.1big.jpg",
			"smallpic":"img/5.1small.jpg",
			"colorpic":"img/5.1color.jpg|img/5.2color.jpg|img/5.3color.jpg|img/5.4color.jpg",
			"color":"白色|黄色|绿色|粉色"
		},
		{
			"id":"6",
			"title":"VINCI智能头机 大存储音乐播放器+Hi-Fi耳机+高精传感器",
			"intro":"img/1.1intro.jpg|img/1.2intro.jpg|img/1.3intro.jpg",
			"price":"￥ 158.00",
			"num":1,
			"pic":"img/5.jpg",
			"origin":"img/cn.jpg|中国",
			"parents":"g-jr-sh-xw",
			"kind":"new",
			"code":"93649110-1",
			"bigpic":"img/5.1big.jpg",
			"smallpic":"img/5.1small.jpg",
			"colorpic":"img/5.1color.jpg|img/5.2color.jpg|img/5.3color.jpg|img/5.4color.jpg",
			"color":"白色|黄色|绿色|粉色"
		},
		{
			"id":"7",
			"title":"费驰 纯银纤维抗菌除臭吸汗排汗运动袜 两双/盒 全国包邮",
			"intro":"img/1.1intro.jpg|img/1.2intro.jpg|img/1.3intro.jpg",
			"price":"￥ 158.00",
			"num":1,
			"pic":"img/6.jpg",
			"origin":"img/cn.jpg|中国",
			"parents":"g-jr-sh-xw",
			"kind":"hot",
			"code":"93649110-1",
			"bigpic":"img/6.1big.jpg",
			"smallpic":"img/6.1small.jpg",
			"colorpic":"",
			"color":""
		},
		{
			"id":"8",
			"title":"费驰 纯银纤维抗菌除臭吸汗排汗运动袜 两双/盒 全国包邮",
			"intro":"img/1.1intro.jpg|img/1.2intro.jpg|img/1.3intro.jpg",
			"price":"￥ 158.00",
			"num":1,
			"pic":"img/7.jpg",
			"origin":"img/cn.jpg|中国",
			"parents":"g-jr-sh-xw",
			"kind":"hot",
			"code":"93649110-1",
			"bigpic":"img/7.1big.jpg",
			"smallpic":"img/7.1small.jpg",
			"colorpic":"",
			"color":""
		},
		{
			"id":"9",
			"title":"费驰 纯银纤维抗菌除臭吸汗排汗运动袜 两双/盒 全国包邮",
			"intro":"img/1.1intro.jpg|img/1.2intro.jpg|img/1.3intro.jpg",
			"price":"￥ 158.00",
			"num":1,
			"pic":"img/8.jpg",
			"origin":"img/cn.jpg|中国",
			"parents":"g-jr-sh-xw",
			"kind":"hot",
			"code":"93649110-1",
			"bigpic":"img/8.1big.jpg",
			"smallpic":"img/8.1small.jpg",
			"colorpic":"",
			"color":""
		},
		{
			"id":"10",
			"title":"费驰 纯银纤维抗菌除臭吸汗排汗运动袜 两双/盒 全国包邮",
			"intro":"img/1.1intro.jpg|img/1.2intro.jpg|img/1.3intro.jpg",
			"price":"￥ 158.00",
			"num":1,
			"pic":"img/9.jpg",
			"origin":"img/cn.jpg|中国",
			"parents":"g-jr-sh-xw",
			"kind":"hot",
			"code":"93649110-1",
			"bigpic":"img/9.1big.jpg|img",
			"smallpic":"img/9.1small.jpg",
			"colorpic":"",
			"color":""
		},
		{
			"id":"8",
			"title":"费驰 纯银纤维抗菌除臭吸汗排汗运动袜 两双/盒 全国包邮",
			"intro":"img/1.1intro.jpg|img/1.2intro.jpg|img/1.3intro.jpg",
			"price":"￥ 158.00",
			"num":1,
			"pic":"img/7.jpg",
			"origin":"img/cn.jpg|中国",
			"parents":"g-jr-sh-xw",
			"kind":"hot",
			"code":"93649110-1",
			"bigpic":"img/7.1big.jpg",
			"smallpic":"img/7.1small.jpg",
			"colorpic":"",
			"color":""
		},
		{
			"id":"11",
			"title":"费驰 纯银纤维抗菌除臭吸汗排汗运动袜 两双/盒 全国包邮",
			"intro":"img/1.1intro.jpg|img/1.2intro.jpg|img/1.3intro.jpg",
			"price":"￥ 158.00",
			"num":1,
			"pic":"img/10.jpg",
			"origin":"img/cn.jpg|中国",
			"parents":"g-jr-sh-xw",
			"kind":"hot",
			"code":"93649110-1",
			"bigpic":"img/10.1big.jpg",
			"smallpic":"img/10.1small.jpg",
			"colorpic":"",
			"color":""
		},
		{
			"id":"12",
			"title":"费驰 纯银纤维抗菌除臭吸汗排汗运动袜 两双/盒 全国包邮",
			"intro":"img/1.1intro.jpg|img/1.2intro.jpg|img/1.3intro.jpg",
			"price":"￥ 158.00",
			"num":1,
			"pic":"img/11.jpg",
			"origin":"img/cn.jpg|中国",
			"parents":"g-jr-sh-xw",
			"kind":"hot",
			"code":"93649110-1",
			"bigpic":"img/11.1big.jpg",
			"smallpic":"img/11.1small.jpg",
			"colorpic":"",
			"color":""
		},
		{
			"id":"13",
			"title":"费驰 纯银纤维抗菌除臭吸汗排汗运动袜 两双/盒 全国包邮",
			"intro":"img/1.1intro.jpg|img/1.2intro.jpg|img/1.3intro.jpg",
			"price":"￥ 158.00",
			"num":1,
			"pic":"img/12.jpg",
			"origin":"img/cn.jpg|中国",
			"parents":"g-jr-sh-xw",
			"kind":"hot",
			"code":"93649110-1",
			"bigpic":"img/12.1big.jpg",
			"smallpic":"img/12.1small.jpg",
			"colorpic":"",
			"color":""
		},
		{
			"id":"14",
			"title":"费驰 纯银纤维抗菌除臭吸汗排汗运动袜 两双/盒 全国包邮",
			"intro":"img/1.1intro.jpg|img/1.2intro.jpg|img/1.3intro.jpg",
			"price":"￥ 158.00",
			"num":1,
			"pic":"img/13.jpg",
			"origin":"img/cn.jpg|中国",
			"parents":"g-jr-sh-xw",
			"kind":"hot",
			"code":"93649110-1",
			"bigpic":"img/13.1big.jpg",
			"smallpic":"img/13.1small.jpg",
			"colorpic":"",
			"color":""
		},
		{
			"id":"14",
			"title":"费驰 纯银纤维抗菌除臭吸汗排汗运动袜 两双/盒 全国包邮",
			"intro":"img/1.1intro.jpg|img/1.2intro.jpg|img/1.3intro.jpg",
			"price":"￥ 158.00",
			"num":1,
			"pic":"img/13.jpg",
			"origin":"img/cn.jpg|中国",
			"parents":"g-jr-sh-xw",
			"kind":"hot",
			"code":"93649110-1",
			"bigpic":"img/13.1big.jpg",
			"smallpic":"img/13.1small.jpg",
			"colorpic":"",
			"color":""
		},
		{
			"id":"15",
			"title":"费驰 纯银纤维抗菌除臭吸汗排汗运动袜 两双/盒 全国包邮",
			"intro":"img/1.1intro.jpg|img/1.2intro.jpg|img/1.3intro.jpg",
			"price":"￥ 158.00",
			"num":1,
			"pic":"img/14.jpg",
			"origin":"img/cn.jpg|中国",
			"parents":"g-jr-sh-xw",
			"kind":"free",			
			"code":"93649110-1",
			"bigpic":"img/14.1big.jpg",
			"smallpic":"img/14.1small.jpg",
			"colorpic":"",
			"color":""
		},
		{
			"id":"16",
			"title":"费驰 纯银纤维抗菌除臭吸汗排汗运动袜 两双/盒 全国包邮",
			"intro":"img/1.1intro.jpg|img/1.2intro.jpg|img/1.3intro.jpg",
			"price":"￥ 158.00",
			"num":1,
			"pic":"img/15.jpg",
			"origin":"img/cn.jpg|中国",
			"parents":"g-jr-sh-xw",
			"kind":"free",
			"code":"93649110-1",
			"bigpic":"img/15.1big.jpg",
			"smallpic":"img/15.1small.jpg",
			"colorpic":"",
			"color":""
		},
		{
			"id":"17",
			"title":"费驰 纯银纤维抗菌除臭吸汗排汗运动袜 两双/盒 全国包邮",
			"intro":"img/1.1intro.jpg|img/1.2intro.jpg|img/1.3intro.jpg",
			"price":"￥ 158.00",
			"num":1,
			"pic":"img/16.jpg",
			"origin":"img/cn.jpg|中国",
			"parents":"g-jr-sh-xw",
			"kind":"free",
			"code":"93649110-1",
			"bigpic":"img/16.1big.jpg",
			"smallpic":"img/16.1small.jpg",
			"colorpic":"",
			"color":""
		},
		{
			"id":"18",
			"title":"费驰 纯银纤维抗菌除臭吸汗排汗运动袜 两双/盒 全国包邮",
			"intro":"img/1.1intro.jpg|img/1.2intro.jpg|img/1.3intro.jpg",
			"price":"￥ 158.00",
			"num":1,
			"pic":"img/17.jpg",
			"origin":"img/cn.jpg|中国",
			"parents":"g-jr-sh-xw",
			"kind":"free",
			"code":"93649110-1",
			"bigpic":"img/17.1big.jpg",
			"smallpic":"img/17.1small.jpg",
			"colorpic":"",
			"color":""
		},
		{
			"id":"19",
			"title":"费驰 纯银纤维抗菌除臭吸汗排汗运动袜 两双/盒 全国包邮",
			"intro":"img/1.1intro.jpg|img/1.2intro.jpg|img/1.3intro.jpg",
			"price":"￥ 158.00",
			"num":1,
			"pic":"img/18.jpg",
			"origin":"img/cn.jpg|中国",
			"parents":"g-jr-sh-xw",
			"kind":"free",
			"code":"93649110-1",
			"bigpic":"img/18.1big.jpg",
			"smallpic":"img/18.1small.jpg",
			"colorpic":"",
			"color":""
		},
		{
			"id":"20",
			"title":"费驰 纯银纤维抗菌除臭吸汗排汗运动袜 两双/盒 全国包邮",
			"intro":"img/1.1intro.jpg|img/1.2intro.jpg|img/1.3intro.jpg",
			"price":"￥ 158.00",
			"num":1,
			"pic":"img/19.jpg",
			"origin":"img/cn.jpg|中国",
			"parents":"g-jr-sh-xw",
			"kind":"free",
			"code":"93649110-1",
			"bigpic":"img/19.1big.jpg",
			"smallpic":"img/19.1small.jpg",
			"colorpic":"",
			"color":""
		},
		{
			"id":"21",
			"title":"费驰 纯银纤维抗菌除臭吸汗排汗运动袜 两双/盒 全国包邮",
			"intro":"img/1.1intro.jpg|img/1.2intro.jpg|img/1.3intro.jpg",
			"price":"￥ 158.00",
			"num":1,
			"pic":"img/20.jpg",
			"origin":"img/cn.jpg|中国",
			"parents":"g-jr-sh-xw",
			"kind":"free",
			"code":"93649110-1",
			"bigpic":"img/20.1big.jpg",
			"smallpic":"img/20.1small.jpg",
			"colorpic":"",
			"color":""
		},
		{
			"id":"22",
			"title":"费驰 纯银纤维抗菌除臭吸汗排汗运动袜 两双/盒 全国包邮",
			"intro":"img/1.1intro.jpg|img/1.2intro.jpg|img/1.3intro.jpg",
			"price":"￥ 158.00",
			"num":1,
			"pic":"img/1.jpg",
			"origin":"img/cn.jpg|中国",
			"parents":"g-jr-sh-xw",
			"kind":"free",
			"code":"93649110-1",
			"bigpic":"img/1.1big.jpg|img/1.2big.jpg|img/1.3big.jpg",
			"smallpic":"img/1.1small.jpg|img/1.2small.jpg|img/1.3small.jpg",
			"colorpic":"img/1.1color.jpg|img/1.2color.jpg",
			"color":"黑色|白色"
		},
		{
			"id":"23",
			"title":"费驰 纯银纤维抗菌除臭吸汗排汗运动袜 两双/盒 全国包邮",
			"intro":"img/1.1intro.jpg|img/1.2intro.jpg|img/1.3intro.jpg",
			"price":"￥ 158.00",
			"num":1,
			"pic":"img/1.jpg",
			"origin":"img/cn.jpg|中国",
			"parents":"g-jr-sh-xw",
			"kind":"free",
			"code":"93649110-1",
			"bigpic":"img/1.1big.jpg|img/1.2big.jpg|img/1.3big.jpg",
			"smallpic":"img/1.1small.jpg|img/1.2small.jpg|img/1.3small.jpg",
			"colorpic":"img/1.1color.jpg|img/1.2color.jpg",
			"color":"黑色|白色"
		},
		{
			"id":"23",
			"title":"费驰 纯银纤维抗菌除臭吸汗排汗运动袜 两双/盒 全国包邮",
			"intro":"img/1.1intro.jpg|img/1.2intro.jpg|img/1.3intro.jpg",
			"price":"￥ 158.00",
			"num":1,
			"pic":"img/1.jpg",
			"origin":"img/cn.jpg|中国",
			"parents":"g-jr-sh-xw",
			"kind":"free",
			"code":"93649110-1",
			"bigpic":"img/1.1big.jpg|img/1.2big.jpg|img/1.3big.jpg",
			"smallpic":"img/1.1small.jpg|img/1.2small.jpg|img/1.3small.jpg",
			"colorpic":"img/1.1color.jpg|img/1.2color.jpg",
			"color":"黑色|白色"
		},
		{
			"id":"24",
			"title":"费驰 纯银纤维抗菌除臭吸汗排汗运动袜 两双/盒 全国包邮",
			"intro":"img/1.1intro.jpg|img/1.2intro.jpg|img/1.3intro.jpg",
			"price":"￥ 158.00",
			"num":1,
			"pic":"img/1.jpg",
			"origin":"img/cn.jpg|中国",
			"parents":"g-jr-sh-xw",
			"kind":"promote",
			"code":"93649110-1",
			"bigpic":"img/1.1big.jpg|img/1.2big.jpg|img/1.3big.jpg",
			"smallpic":"img/1.1small.jpg|img/1.2small.jpg|img/1.3small.jpg",
			"colorpic":"img/1.1color.jpg|img/1.2color.jpg",
			"color":"黑色|白色"
		},
		{
			"id":"25",
			"title":"费驰 纯银纤维抗菌除臭吸汗排汗运动袜 两双/盒 全国包邮",
			"intro":"img/1.1intro.jpg|img/1.2intro.jpg|img/1.3intro.jpg",
			"price":"￥ 158.00",
			"num":1,
			"pic":"img/1.jpg",
			"origin":"img/cn.jpg|中国",
			"parents":"g-jr-sh-xw",
			"kind":"promote",
			"code":"93649110-1",
			"bigpic":"img/1.1big.jpg|img/1.2big.jpg|img/1.3big.jpg",
			"smallpic":"img/1.1small.jpg|img/1.2small.jpg|img/1.3small.jpg",
			"colorpic":"img/1.1color.jpg|img/1.2color.jpg",
			"color":"黑色|白色"
		},
		{
			"id":"26",
			"title":"费驰 纯银纤维抗菌除臭吸汗排汗运动袜 两双/盒 全国包邮",
			"intro":"img/1.1intro.jpg|img/1.2intro.jpg|img/1.3intro.jpg",
			"price":"￥ 158.00",
			"num":1,
			"pic":"img/1.jpg",
			"origin":"img/cn.jpg|中国",
			"parents":"g-jr-sh-xw",
			"kind":"promote",
			"code":"93649110-1",
			"bigpic":"img/1.1big.jpg|img/1.2big.jpg|img/1.3big.jpg",
			"smallpic":"img/1.1small.jpg|img/1.2small.jpg|img/1.3small.jpg",
			"colorpic":"img/1.1color.jpg|img/1.2color.jpg",
			"color":"黑色|白色"
		},
		{
			"id":"27",
			"title":"费驰 纯银纤维抗菌除臭吸汗排汗运动袜 两双/盒 全国包邮",
			"intro":"img/1.1intro.jpg|img/1.2intro.jpg|img/1.3intro.jpg",
			"price":"￥ 158.00",
			"num":1,
			"pic":"img/1.jpg",
			"origin":"img/cn.jpg|中国",
			"parents":"g-jr-sh-xw",
			"kind":"promote",
			"code":"93649110-1",
			"bigpic":"img/1.1big.jpg|img/1.2big.jpg|img/1.3big.jpg",
			"smallpic":"img/1.1small.jpg|img/1.2small.jpg|img/1.3small.jpg",
			"colorpic":"img/1.1color.jpg|img/1.2color.jpg",
			"color":"黑色|白色"
		},
		{
			"id":"28",
			"title":"费驰 纯银纤维抗菌除臭吸汗排汗运动袜 两双/盒 全国包邮",
			"intro":"img/1.1intro.jpg|img/1.2intro.jpg|img/1.3intro.jpg",
			"price":"￥ 158.00",
			"num":1,
			"pic":"img/1.jpg",
			"origin":"img/cn.jpg|中国",
			"parents":"g-jr-sh-xw",
			"kind":"promote",
			"code":"93649110-1",
			"bigpic":"img/1.1big.jpg|img/1.2big.jpg|img/1.3big.jpg",
			"smallpic":"img/1.1small.jpg|img/1.2small.jpg|img/1.3small.jpg",
			"colorpic":"img/1.1color.jpg|img/1.2color.jpg",
			"color":"黑色|白色"
		},
		{
			"id":"29",
			"title":"费驰 纯银纤维抗菌除臭吸汗排汗运动袜 两双/盒 全国包邮",
			"intro":"img/1.1intro.jpg|img/1.2intro.jpg|img/1.3intro.jpg",
			"price":"￥ 158.00",
			"num":1,
			"pic":"img/1.jpg",
			"origin":"img/cn.jpg|中国",
			"parents":"g-jr-sh-xw",
			"kind":"hot",
			"code":"93649110-1",
			"bigpic":"img/1.1big.jpg|img/1.2big.jpg|img/1.3big.jpg",
			"smallpic":"img/1.1small.jpg|img/1.2small.jpg|img/1.3small.jpg",
			"colorpic":"img/1.1color.jpg|img/1.2color.jpg",
			"color":"黑色|白色"
		},
		{
			"id":"30",
			"title":"费驰 纯银纤维抗菌除臭吸汗排汗运动袜 两双/盒 全国包邮",
			"intro":"img/1.1intro.jpg|img/1.2intro.jpg|img/1.3intro.jpg",
			"price":"￥ 158.00",
			"num":1,
			"pic":"img/1.jpg",
			"origin":"img/cn.jpg|中国",
			"parents":"g-jr-sh-xw",
			"kind":"promote",
			"code":"93649110-1",
			"bigpic":"img/1.1big.jpg|img/1.2big.jpg|img/1.3big.jpg",
			"smallpic":"img/1.1small.jpg|img/1.2small.jpg|img/1.3small.jpg",
			"colorpic":"img/1.1color.jpg|img/1.2color.jpg",
			"color":"黑色|白色"
		},
		{
			"id":"31",
			"title":"费驰 纯银纤维抗菌除臭吸汗排汗运动袜 两双/盒 全国包邮",
			"intro":"img/1.1intro.jpg|img/1.2intro.jpg|img/1.3intro.jpg",
			"price":"￥ 158.00",
			"num":1,
			"pic":"img/1.jpg",
			"origin":"img/cn.jpg|中国",
			"parents":"g-jr-sh-xw",
			"kind":"promote",
			"code":"93649110-1",
			"bigpic":"img/1.1big.jpg|img/1.2big.jpg|img/1.3big.jpg",
			"smallpic":"img/1.1small.jpg|img/1.2small.jpg|img/1.3small.jpg",
			"colorpic":"img/1.1color.jpg|img/1.2color.jpg",
			"color":"黑色|白色"
		}
		
	],
	"goods":[
		{
			"id":"1",
			"title":"雪域牛乳芝士蛋糕",
			"intro":"img/1.1intro.jpg|img/1.2intro.jpg|img/1.3intro.jpg",
			"price":158,
			"num":1,
			"pic":"img/18.jpg"
		},
		{
			"id":"2",
			"title":"提拉米苏乐脆蛋糕",
			"intro":"img/1.1intro.jpg|img/1.2intro.jpg|img/1.3intro.jpg",
			"price":198,
			"num":1,
			"pic":"img/2.jpg"
		}
		
	]
}
